arcor2_kinect_azure_data/VERSION
arcor2_kinect_azure_data/__init__.py
arcor2_kinect_azure_data/aggregation.py
arcor2_kinect_azure_data/joint.py
arcor2_kinect_azure_data/py.typed
arcor2_kinect_azure_data/settings.py
arcor2_kinect_azure_data/data/kinect_azure.dae
arcor2_kinect_azure_data/object_types/__init__.py
arcor2_kinect_azure_data/object_types/kinect_azure.py
arcor2_kinect_azure_data-0.2.0.dist-info/METADATA
arcor2_kinect_azure_data-0.2.0.dist-info/WHEEL
arcor2_kinect_azure_data-0.2.0.dist-info/entry_points.txt
arcor2_kinect_azure_data-0.2.0.dist-info/namespace_packages.txt
arcor2_kinect_azure_data-0.2.0.dist-info/top_level.txt
arcor2_kinect_azure_data-0.2.0.dist-info/RECORD
